fixtures/__init__.py
fixtures/fifa.py
fixtures/fifawc.py
fifa_simulator-1.0.2.dist-info/LICENSE
fifa_simulator-1.0.2.dist-info/METADATA
fifa_simulator-1.0.2.dist-info/WHEEL
fifa_simulator-1.0.2.dist-info/top_level.txt
fifa_simulator-1.0.2.dist-info/RECORD
